pypricklybird/__init__.py
pypricklybird/converter.py
pypricklybird-1.0.3.dist-info/METADATA
pypricklybird-1.0.3.dist-info/WHEEL
pypricklybird-1.0.3.dist-info/licenses/LICENSE
pypricklybird-1.0.3.dist-info/RECORD
