Metadata-Version: 2.4
Name: pypricklybird
Version: 1.0.3
Summary: Python library to encode and decode pricklybird.
Project-URL: Documentation, https://github.com/ndornseif/pypricklybird#readme
Project-URL: Issues, https://github.com/ndornseif/pypricklybird/issues
Project-URL: Source, https://github.com/ndornseif/pypricklybird
Author-email: ndornseif <5382403+ndornseif@users.noreply.github.com>
License-Expression: MIT
License-File: LICENSE
Classifier: Development Status :: 5 - Production/Stable
Classifier: Intended Audience :: Developers
Classifier: License :: OSI Approved :: MIT License
Classifier: Natural Language :: English
Classifier: Operating System :: OS Independent
Classifier: Programming Language :: Python
Classifier: Programming Language :: Python :: 3.12
Classifier: Programming Language :: Python :: 3.13
Classifier: Programming Language :: Python :: Implementation :: CPython
Classifier: Topic :: Scientific/Engineering :: Human Machine Interfaces
Classifier: Topic :: Software Development :: User Interfaces
Requires-Python: >=3.12
